transnet_generator/__init__.py
transnet_generator/generator.py
transnet_generator-0.1.dist-info/LICENCE
transnet_generator-0.1.dist-info/METADATA
transnet_generator-0.1.dist-info/WHEEL
transnet_generator-0.1.dist-info/top_level.txt
transnet_generator-0.1.dist-info/RECORD
