Metadata-Version: 2.1
Name: transnet-generator
Version: 0.1
Summary: TransNet Generator is a Python library for generating transport network from GTFS data.
Author: B. Walleth
Project-URL: Homepage, https://github.com/2023-Ljubljana-ERASMUS/transnet-generator
Classifier: Programming Language :: Python :: 3
Classifier: License :: OSI Approved :: MIT License
Classifier: Operating System :: OS Independent
Requires-Python: >=3.8
License-File: LICENCE
